fpe_plus/__init__.py
fpe_plus/core.py
fpe_plus/csv_utils.py
fpe_plus/types.py
fpe_plus-1.1.1.dist-info/LICENSE
fpe_plus-1.1.1.dist-info/METADATA
fpe_plus-1.1.1.dist-info/WHEEL
fpe_plus-1.1.1.dist-info/top_level.txt
fpe_plus-1.1.1.dist-info/RECORD
