Metadata-Version: 2.1
Name: fpe-plus
Version: 1.1.1
Summary: Format Preserving Encryption with support for dates, numbers, floats, and strings with any character
Home-page: https://github.com/vasudevjaiswal/fpe_plus
Author: Vasudev Jaiswal
Author-email: vasudevjaiswal786@gmail.com
License: UNKNOWN
Platform: UNKNOWN
Classifier: Programming Language :: Python :: 3
Classifier: Programming Language :: Python :: 3.7
Classifier: Programming Language :: Python :: 3.8
Classifier: Programming Language :: Python :: 3.9
Classifier: Programming Language :: Python :: 3.10
Classifier: License :: OSI Approved :: MIT License
Classifier: Operating System :: OS Independent
Requires-Python: >=3.7
License-File: LICENSE
